internet_eng_znu/__init__.py
internet_eng_znu/keymanager.py
internet_eng_znu/main.py
internet_eng_znu/public_key.pem
internet_eng_znu-0.1.15.dist-info/METADATA
internet_eng_znu-0.1.15.dist-info/WHEEL
internet_eng_znu-0.1.15.dist-info/entry_points.txt
internet_eng_znu-0.1.15.dist-info/top_level.txt
internet_eng_znu-0.1.15.dist-info/RECORD
