Metadata-Version: 2.1
Name: internet-eng-znu
Version: 0.1.15
Summary: Deploy your projects on the ZNU server.
Home-page: UNKNOWN
Author: Ali Safapour
Author-email: thisisalinton@gmail.com
License: UNKNOWN
Platform: UNKNOWN
Classifier: Programming Language :: Python :: 3
Classifier: License :: Other/Proprietary License
Classifier: Operating System :: OS Independent
Requires-Python: >=3.10
